senlin_dashboard/__init__.py
senlin_dashboard/exceptions.py
senlin_dashboard/karma.conf.js
senlin_dashboard/api/__init__.py
senlin_dashboard/api/senlin.py
senlin_dashboard/api/utils.py
senlin_dashboard/api/rest/__init__.py
senlin_dashboard/api/rest/senlin.py
senlin_dashboard/cluster/__init__.py
senlin_dashboard/cluster/dashboard.py
senlin_dashboard/cluster/clusters/__init__.py
senlin_dashboard/cluster/clusters/forms.py
senlin_dashboard/cluster/clusters/panel.py
senlin_dashboard/cluster/clusters/tables.py
senlin_dashboard/cluster/clusters/tabs.py
senlin_dashboard/cluster/clusters/tests.py
senlin_dashboard/cluster/clusters/urls.py
senlin_dashboard/cluster/clusters/views.py
senlin_dashboard/cluster/clusters/templates/clusters/_create.html
senlin_dashboard/cluster/clusters/templates/clusters/_detail_nodes.html
senlin_dashboard/cluster/clusters/templates/clusters/_detail_overview.html
senlin_dashboard/cluster/clusters/templates/clusters/_manage_policies.html
senlin_dashboard/cluster/clusters/templates/clusters/create.html
senlin_dashboard/cluster/clusters/templates/clusters/index.html
senlin_dashboard/cluster/clusters/templates/clusters/manage_policies.html
senlin_dashboard/cluster/nodes/__init__.py
senlin_dashboard/cluster/nodes/event_tables.py
senlin_dashboard/cluster/nodes/forms.py
senlin_dashboard/cluster/nodes/panel.py
senlin_dashboard/cluster/nodes/tables.py
senlin_dashboard/cluster/nodes/tabs.py
senlin_dashboard/cluster/nodes/tests.py
senlin_dashboard/cluster/nodes/urls.py
senlin_dashboard/cluster/nodes/views.py
senlin_dashboard/cluster/nodes/templates/nodes/_create.html
senlin_dashboard/cluster/nodes/templates/nodes/_detail_event.html
senlin_dashboard/cluster/nodes/templates/nodes/_detail_overview.html
senlin_dashboard/cluster/nodes/templates/nodes/_update.html
senlin_dashboard/cluster/nodes/templates/nodes/create.html
senlin_dashboard/cluster/nodes/templates/nodes/index.html
senlin_dashboard/cluster/nodes/templates/nodes/update.html
senlin_dashboard-8.0.0.dist-info/AUTHORS
senlin_dashboard-8.0.0.dist-info/LICENSE
senlin_dashboard-8.0.0.dist-info/METADATA
senlin_dashboard-8.0.0.dist-info/WHEEL
senlin_dashboard-8.0.0.dist-info/pbr.json
senlin_dashboard-8.0.0.dist-info/top_level.txt
senlin_dashboard-8.0.0.dist-info/RECORD
