Metadata-Version: 2.1
Name: senlin-dashboard
Version: 8.0.0
Summary: Senlin Dashboard
Home-page: https://docs.openstack.org/senlin-dashboard/latest/
Author: OpenStack
Author-email: openstack-discuss@lists.openstack.org
License: Apache License, Version 2.0
Platform: UNKNOWN
Classifier: Programming Language :: Python
Classifier: Programming Language :: Python :: 3
Classifier: Programming Language :: Python :: 3.6
Classifier: Programming Language :: Python :: 3.7
Classifier: Programming Language :: Python :: 3.8
Classifier: Programming Language :: Python :: 3.9
Classifier: Environment :: OpenStack
Classifier: Intended Audience :: Information Technology
Classifier: Intended Audience :: System Administrators
Classifier: License :: OSI Approved :: Apache Software License
Classifier: Operating System :: POSIX :: Linux
Requires-Dist: PyYAML (>=3.12)
Requires-Dist: horizon (>=17.1.0)
Requires-Dist: pbr (!=2.1.0,>=2.0.0)
Requires-Dist: python-senlinclient (>=1.9.0)
